[
  {
    "id": "1",
    "created": "2017-08-08",
    "updated": "2017-08-08",
    "category": "sports",
    "subcategory": "hockey",
    "title": "All Time NHL Goal Scorers",
    "source_1": "Wayne Gretzky",
    "source_2": "Gordie Howe",
    "source_3":"Jaromir Jagr",
    "source_4": "Brett Hull",
    "source_5":"Marcel Dionne",
    "target_1":"894",
    "target_2":"801",
    "target_3":"765",
    "target_4":"741",
    "target_5":"731",
    "source": "http://www.quanthockey.com/nhl/records/nhl-players-all-time-goals-leaders.html"
  },
  {
    "id": "2",
    "created": "2017-07-08",
    "updated": "2017-07-08",
    "category": "sports",
    "subcategory": "basketball",
    "title": "All Time NBA Points Leaders",
    "source_1": "Kareem Abdul-Jabbar",
    "source_2": "Karl Malquestion",
    "source_3": "Kobe Bryant",
    "source_4": "Michael Jordan",
    "source_5": "Wilt Chamberlain",
    "target_1":"38,387",
    "target_2":"36,928",
    "target_3":"33,643",
    "target_4":"32,292",
    "target_5":"31,419",
    "source": "http://www.espn.com/nba/history/leaders"
  },
  {
    "id": "3",
    "created": "2017-07-08",
    "updated": "2017-07-08",
    "category": "sports",
    "subcategory": "soccer",
    "title": "Top 10 goalscorers of all time",
    "source_1": "Arthur Friedenreich",
    "source_2": "Pele",
    "source_3": "Josef Bican",
    "source_4": "Romario",
    "source_5": "Gerd Muller",
    "target_1":"1,329",
    "target_2":"1,281",
    "target_3":"805",
    "target_4":"743",
    "target_5":"711",
    "source": "https://www.sportskeeda.com/football/top-10-goalscorers-of-all-time/5"
  },
  {
    "id": "4",
    "created": "2017-07-08",
    "updated": "2017-07-08",
    "category": "sports",
    "subcategory": "soccer",
    "title": "Most career goals scored in football",
    "source_1": "Christiano Ronaldo",
    "source_2": "Leo Messi",
    "source_3": "Zlatan Ibrahimovic",
    "source_4": "Samual Etos",
    "source_5": "David Villa",
    "target_1":"573",
    "target_2":"548",
    "target_3":"472",
    "target_4":"389",
    "target_5":"388",
    "source": "https://talksport.com/football/most-career-goals-scored-football-top-10-including-lisource_1l-messi-cristiano-ronaldo-zlatan?p=0"
  },
  {
    "id": "5",
    "created": "2017-07-08",
    "updated": "2017-07-08",
    "category": "sports",
    "subcategory": "hockey",
    "title": "Most Stanley Cup Wins by Team",
    "source_1": "Montreal Canadiens",
    "source_2": "Toronto Maple Leafs",
    "source_3": "Boston Bruins",
    "source_4": "Edmonton Oilers",
    "source_5": "New York Rangers",
    "target_1":"23",
    "target_2":"13",
    "target_3":"6",
    "target_4":"5",
    "target_5":"4",
    "source": "https://www.thoughtco.com/most-stanley-cup-wins-by-team-2779436"
  }
]
